virtualserialports.py
PyVirtualSerialPorts-1.0.1.dist-info/LICENSE
PyVirtualSerialPorts-1.0.1.dist-info/METADATA
PyVirtualSerialPorts-1.0.1.dist-info/WHEEL
PyVirtualSerialPorts-1.0.1.dist-info/entry_points.txt
PyVirtualSerialPorts-1.0.1.dist-info/top_level.txt
PyVirtualSerialPorts-1.0.1.dist-info/RECORD
