Metadata-Version: 2.1
Name: PyVirtualSerialPorts
Version: 1.0.1
Summary: *nix virtual serial ports
Home-page: https://github.com/ezramorris/PyVirtualSerialPorts
Author: Ezra Morris
License: UNKNOWN
Platform: UNKNOWN
Classifier: Programming Language :: Python :: 3
Classifier: License :: OSI Approved :: MIT License
Classifier: Operating System :: POSIX
Classifier: Intended Audience :: Developers
Requires-Python: >=3.5
